craftext/__init__.py
craftext/dataset/__init__.py
craftext/dataset/configs/build_line_hard_test_other_params.yaml
craftext/dataset/configs/build_line_hard_test_paraphrases.yaml
craftext/dataset/configs/build_line_hard_train.yaml
craftext/dataset/configs/build_line_medium_test_other_params.yaml
craftext/dataset/configs/build_line_medium_test_paraphrases.yaml
craftext/dataset/configs/build_line_medium_train.yaml
craftext/dataset/configs/build_square_hard_test_other_params.yaml
craftext/dataset/configs/build_square_hard_test_paraphrases.yaml
craftext/dataset/configs/build_square_hard_train.yaml
craftext/dataset/configs/build_square_medium_test_other_params.yaml
craftext/dataset/configs/build_square_medium_test_paraphrases.yaml
craftext/dataset/configs/build_square_medium_train.yaml
craftext/dataset/configs/build_star_hard_test_other_params.yaml
craftext/dataset/configs/build_star_hard_test_paraphrases.yaml
craftext/dataset/configs/build_star_hard_train.yaml
craftext/dataset/configs/build_star_medium_test_other_params.yaml
craftext/dataset/configs/build_star_medium_test_paraphrases.yaml
craftext/dataset/configs/build_star_medium_train.yaml
craftext/dataset/configs/conditional_achievements_hard_test_other_params.yaml
craftext/dataset/configs/conditional_achievements_hard_test_paraphrases.yaml
craftext/dataset/configs/conditional_achievements_hard_train.yaml
craftext/dataset/configs/conditional_achievements_medium_test_other_params.yaml
craftext/dataset/configs/conditional_achievements_medium_test_paraphrases.yaml
craftext/dataset/configs/conditional_achievements_medium_train.yaml
craftext/dataset/configs/conditional_placing_hard_test_other_params.yaml
craftext/dataset/configs/conditional_placing_hard_test_paraphrases.yaml
craftext/dataset/configs/conditional_placing_hard_train.yaml
craftext/dataset/configs/conditional_placing_medium_test_other_params.yaml
craftext/dataset/configs/conditional_placing_medium_test_paraphrases.yaml
craftext-0.2.2.dist-info/METADATA
craftext-0.2.2.dist-info/WHEEL
craftext-0.2.2.dist-info/RECORD
