Metadata-Version: 2.3
Name: CrafText
Version: 0.2.2
Summary: A text processing package with various scenarios and checkers.
License: MIT
Author: ZoyaV
Requires-Python: >=3.9
Classifier: License :: OSI Approved :: MIT License
Classifier: Programming Language :: Python :: 3
Classifier: Programming Language :: Python :: 3.9
Classifier: Programming Language :: Python :: 3.10
Classifier: Programming Language :: Python :: 3.11
Classifier: Programming Language :: Python :: 3.12
Classifier: Programming Language :: Python :: 3.13
Requires-Dist: craftax (==1.4.3)
Requires-Dist: dm-tree (==0.1.8)
Requires-Dist: etils (==0.9.0)
Requires-Dist: flax (==0.8.5)
Requires-Dist: numpy (>=1.26.0)
Requires-Dist: transformers (==4.44.2)
Project-URL: Documentation, https://github.com/ZoyaV/CrafText#readme
Project-URL: Homepage, https://github.com/ZoyaV/CrafText
Project-URL: Repository, https://github.com/ZoyaV/CrafText
